Sequencial/decode.v
// DECODE BLOCK

module decode(clk, icode, rA, rB, valA, valB);

    input clk;
    input [3:0] icode;
    input [3:0] rA;
    input [3:0] rB;

    output reg [63:0] valA;
    output reg [63:0] valB;

    reg [63:0] Reg_File[0:14];

    integer i;

    initial
    begin
        valA = 64'd0;
        valB = 64'd0;
    end

   always@(posedge clk)
    begin

        $readmemh("reg_file.txt", Reg_File);
        
    end

    always@(*)
    begin

        if(clk == 1)

            case (icode)
        // Halt
        4'd0: begin
            // valA ← R[rA]
            valA = Reg_File[rA];    
        end
        // NOP
        4'd1: begin
            // valA ← R[rA]
            valA = Reg_File[rA];
                
            // valB ← R[rB]
            valB = Reg_File[rB];
        end
        // rrmovq and cmovXX
        4'd2: begin
            valA = Reg_File[rA];

        end

        // rmmovq
        4'd4: begin
            // valA ← R[rA]
            valA = Reg_File[rA];
                
            // valB ← R[rB]
            valB = Reg_File[rB];
        end
        // mrmovq
        4'd5: begin
            // valB ← R[rB]
            valB = Reg_File[rB];
        end
        // Opq
        4'd6: begin
            // valA ← R[rA]
            valA = Reg_File[rA];
                
            // valB ← R[rB]
            valB = Reg_File[rB];
        end
        // jXX

        // call
        4'd8: begin
            // valB ← R[rsp]
            valB = Reg_File[4];
        end
        // ret
        4'd9: begin
            // valA ← R[rsp]
            valA = Reg_File[4];
                
            // valB ← R[rsp]
            valB = Reg_File[4];
        end
        // pushq
        4'd10: begin
            // valA ← R[ra]
            valA = Reg_File[rA];
                
            // valB ← R[rsp]
            valB = Reg_File[4];
        end
        // popq
        4'd11: begin
            // valA ← R[rsp]
            valA = Reg_File[4];
                
            // valB ← R[rsp]
            valB = Reg_File[4];
        end
        // default: begin
        //     instr_valid = 1; // invalid instruction
        // end
    endcase
end

endmodule

Sequencial/decode_tb.v
`timescale 1ns / 10ps

module decode_tb();

    reg clk;
    reg [3:0] icode;
    reg [3:0] rA;
    reg [3:0] rB;

    wire [63:0] valA;
    wire [63:0] valB;

    decode UUT(clk, icode, rA, rB, valA, valB);

    //creating clk
    initial
    begin
        clk = 0;
        repeat (20)  #10 clk = ~clk;
    end

    initial
    begin

        $dumpfile("decode_tb.vcd");
        $dumpvars(0, decode_tb);

        clk=0;
        icode=4'd0;
        rA=4'd0;
        rB=4'd0;

    end

    initial
    begin

        #10
        icode=4'd2;rA=4'd0;rB=4'd14;

        #20
        icode=4'd3;rA=4'd1;rB=4'd0;

        #20
        icode=4'd4;rA=4'd3;rB=4'd4;

        #20
        icode=4'd5;rA=4'd4;rB=4'd10;

        #20
        icode=4'd6;rA=4'd11;rB=4'd5;

        #20
        icode=4'd7;rA=4'd6;rB=4'd7;

        #20
        icode=4'd8;rA=4'd6;rB=4'd7;

        #20
        icode=4'd9;rA=4'd7;rB=4'd8;

        #20
        icode=4'd10;rA=4'd9;rB=4'd10;

        #20
        icode=4'd11;rA=4'd0;rB=4'd1;
    end

    initial 
    begin
		$monitor($time, "\tclk = %d icode = %b rA = %b rB = %b\n\t\t\tvalA = %g valB = %g\n", clk,icode, rA, rB, valA, valB);
	end

endmodule

Sequencial/decode_tb.vcd
$date
	Mon Feb 19 10:02:04 2024
$end
$version
	Icarus Verilog
$end
$timescale
	10ps
$end
$scope module decode_tb $end
$var wire 64 ! valB [63:0] $end
$var wire 64 " valA [63:0] $end
$var reg 1 # clk $end
$var reg 4 $ icode [3:0] $end
$var reg 4 % rA [3:0] $end
$var reg 4 & rB [3:0] $end
$scope module UUT $end
$var wire 1 # clk $end
$var wire 4 ' icode [3:0] $end
$var wire 4 ( rA [3:0] $end
$var wire 4 ) rB [3:0] $end
$var reg 64 * valA [63:0] $end
$var reg 64 + valB [63:0] $end
$upscope $end
$upscope $end
$enddefinitions $end
#0
$dumpvars
b0 +
b0 *
b0 )
b0 (
b0 '
b0 &
b0 %
b0 $
0#
b0 "
b0 !
$end
#1000
b10 "
b10 *
b1110 &
b1110 )
b10 $
b10 '
1#
#2000
0#
#3000
1#
b0 &
b0 )
b1 %
b1 (
b11 $
b11 '
#4000
0#
#5000
b100 !
b100 +
b11 "
b11 *
1#
b100 &
b100 )
b11 %
b11 (
b100 $
b100 '
#6000
0#
#7000
b1010 !
b1010 +
1#
b1010 &
b1010 )
b100 %
b100 (
b101 $
b101 '
#8000
0#
#9000
b101 !
b101 +
b1011 "
b1011 *
1#
b101 &
b101 )
b1011 %
b1011 (
b110 $
b110 '
#10000
0#
#11000
1#
b111 &
b111 )
b110 %
b110 (
b111 $
b111 '
#12000
0#
#13000
b100 !
b100 +
1#
b1000 $
b1000 '
#14000
0#
#15000
b100 "
b100 *
1#
b1000 &
b1000 )
b111 %
b111 (
b1001 $
b1001 '
#16000
0#
#17000
b1001 "
b1001 *
1#
b1010 &
b1010 )
b1001 %
b1001 (
b1010 $
b1010 '
#18000
0#
#19000
b100 "
b100 *
1#
b1 &
b1 )
b0 %
b0 (
b1011 $
b1011 '
