Sequencial/fetch.v
// FETCH BLOCK

module fetch(clk, PC, icode, ifun, rA, rB, valC, valP, imem_error, instr_valid, hlt);

    input clk;
    input [63:0] PC;
    
    output reg [3:0] icode;
    output reg [3:0] ifun;

    output reg [3:0] rA;
    output reg [3:0] rB;

    output reg [63:0] valC;
    output reg [63:0] valP;

    output reg instr_valid; 
    output reg imem_error;
    output reg hlt;

    reg [0:79] instruction; //Instruction encodings range between 1 and 10 bytes
    reg [7:0] memory[0:1023]; //memory has 256-32 bits words => 1024-8 bits

    reg [0:7] opcode; //operation codes
    reg [0:7] regids; //register IDs

    initial
    begin
        rA = 4'h0;
        rB = 4'h0;
        valC = 64'd0;
        valP = 64'd0;
        hlt = 0;
        instr_valid = 0;
        imem_error = 0;
    end

    // instruction codes
    // Constant values used in HCL descriptions.
    // parameter IHALT   = 4'd0;
    // parameter INOP    = 4'd1;
    // parameter IRRMOVQ = 4'd2; //rrmovq and  cmovXX
    // parameter IIRMOVQ = 4'd3;
    // parameter IRMMOVQ = 4'd4;
    // parameter IMRMOVQ = 4'd5;
    // parameter IOPQ    = 4'd6;
    // parameter IJXX    = 4'd7;
    // parameter ICALL   = 4'd8;
    // parameter IRET    = 4'd9;
    // parameter IPUSHQ  = 4'd10;
    // parameter IPOPQ   = 4'd11;

    initial 
    begin

    // irmovq $0x0, %rax
    memory[0]=8'b00110000; //3 0
    memory[1]=8'b00000000; //F rB=0
    memory[2]=8'b00000000;           
    memory[3]=8'b00000000;           
    memory[4]=8'b00000000;           
    memory[5]=8'b00000000;           
    memory[6]=8'b00000000;           
    memory[7]=8'b00000000;           
    memory[8]=8'b00000000;          
    memory[9]=8'b00000000; //V=0

    // irmovq $0x10, %rdx
    memory[10]=8'b00110000; //3 0
    memory[11]=8'b00000010; //F rB=2
    memory[12]=8'b00000000;           
    memory[13]=8'b00000000;           
    memory[14]=8'b00000000;           
    memory[15]=8'b00000000;           
    memory[16]=8'b00000000;           
    memory[17]=8'b00000000;           
    memory[18]=8'b00000000;          
    memory[19]=8'b00010000; //V=16

    // irmovq $0xc, %rbx
    memory[20]=8'b00110000; //3 0
    memory[21]=8'b00000011; //F rB=3
    memory[22]=8'b00000000;           
    memory[23]=8'b00000000;           
    memory[24]=8'b00000000;           
    memory[25]=8'b00000000;           
    memory[26]=8'b00000000;           
    memory[27]=8'b00000000;           
    memory[28]=8'b00000000;          
    memory[29]=8'b00001100; //V=12

    // jmp check
    memory[30]=8'b01110000; //7 fn
    memory[31]=8'b00000000; //Dest
    memory[32]=8'b00000000; //Dest
    memory[33]=8'b00000000; //Dest
    memory[34]=8'b00000000; //Dest
    memory[35]=8'b00000000; //Dest
    memory[36]=8'b00000000; //Dest
    memory[37]=8'b00000000; //Dest
    memory[38]=8'b00100111; //Dest=39

    // check:
        // addq %rax, %rbx 
        memory[39]=8'b01100000; //5 fn
        memory[40]=8'b00110011; //rA=3 rB=3
        // je rbxres  
        memory[41]=8'b01110011; //7 fn=3
        memory[42]=8'b00000000; //Dest
        memory[43]=8'b00000000; //Dest
        memory[44]=8'b00000000; //Dest
        memory[45]=8'b00000000; //Dest
        memory[46]=8'b00000000; //Dest
        memory[47]=8'b00000000; //Dest
        memory[48]=8'b00000000; //Dest
        memory[49]=8'b01111010; //Dest=122
        // addq %rax, %rdx
        memory[50]=8'b01100000; //5 fn
        memory[51]=8'b00000010; //rA=0 rB=2
        // je rdxres 
        memory[52]=8'b01110011; //7 fn=3
        memory[53]=8'b00000000; //Dest
        memory[54]=8'b00000000; //Dest
        memory[55]=8'b00000000; //Dest
        memory[56]=8'b00000000; //Dest
        memory[57]=8'b00000000; //Dest
        memory[58]=8'b00000000; //Dest
        memory[59]=8'b00000000; //Dest
        memory[60]=8'b01111101; //Dest=125
        // jmp loop2 
        memory[61]=8'b01110000; //7 fn=0
        memory[62]=8'b00000000; //Dest
        memory[63]=8'b00000000; //Dest
        memory[64]=8'b00000000; //Dest
        memory[65]=8'b00000000; //Dest
        memory[66]=8'b00000000; //Dest
        memory[67]=8'b00000000; //Dest
        memory[68]=8'b00000000; //Dest
        memory[69]=8'b01000110; //Dest

        // halt
        memory[70]=8'b00000000; // 0 0

    end


    always@(posedge clk)
    begin

        if(PC > 64'd1023)
        begin

            imem_error = 1; //invalid address        
        end
        else
        begin

            imem_error = 0;

            //Instruction encodings range between 1 and 10 bytes
            instruction = {memory[PC], memory[PC+64'd1], memory[PC+64'd2], memory[PC+64'd3], memory[PC+64'd4], memory[PC+64'd5], memory[PC+64'd6], memory[PC+64'd7], memory[PC+64'd8], memory[PC+64'd9]}; 
    
            //An instruction consists of a 1-byte instruction specifier, 1-byte register specifier, and an 8-byte constant word.

            icode = instruction[0:3];
            ifun = instruction[4:7];


            if(icode < 4'd0 || icode > 4'd11)
            begin

                instr_valid = 1; //invalid instruction
            end
            else
            begin

                instr_valid = 0;
                
    case (icode)
        // Halt
        4'd0: begin
            hlt = 1;
            valP = PC + 64'd1;
        end
        // NOP
        4'd1: begin
            valP = PC + 64'd1;
        end
        // rrmovq and cmovXX
        4'd2: begin
            regids = memory[PC+64'd1];
            rA = regids[0:3];
            rB = regids[4:7];
            valP = PC + 64'd2;
        end
        // irmovq
        4'd3: begin
            regids = memory[PC+64'd1];
            rA = regids[0:3];
            rB = regids[4:7];
            valC = instruction[16:79];
            valP = PC + 64'd10;
        end
        // rmmovq
        4'd4: begin
            regids = instruction[8:15];
            rA = regids[0:3];
            rB = regids[4:7];
            valC = instruction[16:79];
            valP = PC + 64'd10;
        end
        // mrmovq
        4'd5: begin
            regids = instruction[8:15];
            rA = regids[0:3];
            rB = regids[4:7];
            valC = instruction[16:79];
            valP = PC + 64'd10;
        end
        // Opq
        4'd6: begin
            regids = instruction[8:15];
            rA = regids[0:3];
            rB = regids[4:7];
            valP = PC + 64'd2;
        end
        // jXX
        4'd7: begin
            valC = instruction[8:71];
            valP = PC + 64'd9;
        end
        // call
        4'd8: begin
            valC = instruction[8:71];
            valP = PC + 64'd9;
        end
        // ret
        4'd9: begin
            valP = PC + 64'd1;
        end
        // pushq
        4'd10: begin
            regids = instruction[8:15];
            rA = regids[0:3];
            rB = regids[4:7];
            valP = PC + 64'd2;
        end
        // popq
        4'd11: begin
            regids = instruction[8:15];
            rA = regids[0:3];
            rB = regids[4:7];
            valP = PC + 64'd2;
        end
        default: begin
            instr_valid = 1; // invalid instruction
        end
    endcase
end


            end

        end    

    

endmodule

Sequencial/fetch_tb.v
`timescale 1ns / 10ps

module fetch_tb();

  reg clk;
  reg [63:0] PC;
  
  wire [3:0] icode;
  wire [3:0] ifun;

  wire [3:0] rA;
  wire [3:0] rB; 

  wire [63:0] valC;
  wire [63:0] valP;

  output imem_error;
  output instr_valid;
  output hlt;

  fetch UUT(clk, PC, icode, ifun, rA, rB, valC, valP, imem_error, instr_valid, hlt);

  //creating clk
  initial
  begin
    clk = 0;
    repeat (25)  #10 clk = ~clk;
  end

  initial
  begin

    $dumpfile("fetch_tb.vcd");
    $dumpvars(0, fetch_tb);

    clk=0;
    PC=64'd0;

  end
  
  initial 
  begin 

    #10 
    PC=64'd0; 
    
    #20
    PC=valP;
    
    #20
    PC=valP;
    
    #20
    PC=valP;
    
    #20
    PC=valP;
    
    #20
    PC=valP;
    
    #20
    PC=valP;
    
    #20
    PC=valP;
    
    #20
    PC=valP;
    
    #20
    PC=valP;
    
    #20     
    PC=valP;
    
    #20
    PC=64'd1024;    
    
  end 
  
  initial 
  begin
    $monitor($time, "\tclk = %d PC = %g\n\t\t\ticode = %b ifun = %b rA = %b rB = %b valC = %g valP = %g imem_error = %d, instr_valid = %d, hlt = %d\n",clk,PC,icode,ifun,rA,rB,valC,valP,imem_error, instr_valid, hlt);
  end
endmodule

Sequencial/fetch_tb.vcd
$date
	Fri Feb 16 19:27:05 2024
$end
$version
	Icarus Verilog
$end
$timescale
	10ps
$end
$scope module fetch_tb $end
$var wire 64 ! valP [63:0] $end
$var wire 64 " valC [63:0] $end
$var wire 4 # rB [3:0] $end
$var wire 4 $ rA [3:0] $end
$var wire 1 % instr_valid $end
$var wire 1 & imem_error $end
$var wire 4 ' ifun [3:0] $end
$var wire 4 ( icode [3:0] $end
$var wire 1 ) hlt $end
$var reg 64 * PC [63:0] $end
$var reg 1 + clk $end
$scope module UUT $end
$var wire 64 , PC [63:0] $end
$var wire 1 + clk $end
$var reg 1 ) hlt $end
$var reg 4 - icode [3:0] $end
$var reg 4 . ifun [3:0] $end
$var reg 1 & imem_error $end
$var reg 1 % instr_valid $end
$var reg 80 / instruction [0:79] $end
$var reg 4 0 rA [3:0] $end
$var reg 4 1 rB [3:0] $end
$var reg 8 2 regids [0:7] $end
$var reg 64 3 valC [63:0] $end
$var reg 64 4 valP [63:0] $end
$upscope $end
$upscope $end
$enddefinitions $end
#0
$dumpvars
b0 4
b0 3
bx 2
b0 1
b0 0
bx /
bx .
bx -
b0 ,
0+
b0 *
0)
bx (
bx '
0&
0%
b0 $
b0 #
b0 "
b0 !
$end
#1000
b1010 !
b1010 4
b0 2
b0 '
b0 .
b11 (
b11 -
b110000000000000000000000000000000000000000000000000000000000000000000000000000 /
1+
#2000
0+
#3000
b10100 !
b10100 4
b10000 "
b10000 3
b10 #
b10 1
b10 2
b110000000000100000000000000000000000000000000000000000000000000000000000010000 /
1+
b1010 *
b1010 ,
#4000
0+
#5000
b11110 !
b11110 4
b1100 "
b1100 3
b11 #
b11 1
b11 2
b110000000000110000000000000000000000000000000000000000000000000000000000001100 /
1+
b10100 *
b10100 ,
#6000
0+
#7000
b100111 !
b100111 4
b100111 "
b100111 3
b111 (
b111 -
b1110000000000000000000000000000000000000000000000000000000000000010011101100000 /
1+
b11110 *
b11110 ,
#8000
0+
#9000
b101001 !
b101001 4
b11 $
b11 0
b110011 2
b110 (
b110 -
b1100000001100110111001100000000000000000000000000000000000000000000000000000000 /
1+
b100111 *
b100111 ,
#10000
0+
#11000
b110010 !
b110010 4
b1111010 "
b1111010 3
b11 '
b11 .
b111 (
b111 -
b1110011000000000000000000000000000000000000000000000000000000000111101001100000 /
1+
b101001 *
b101001 ,
#12000
0+
#13000
b110100 !
b110100 4
b10 #
b10 1
b0 $
b0 0
b10 2
b0 '
b0 .
b110 (
b110 -
b1100000000000100111001100000000000000000000000000000000000000000000000000000000 /
1+
b110010 *
b110010 ,
#14000
0+
#15000
b111101 !
b111101 4
b1111101 "
b1111101 3
b11 '
b11 .
b111 (
b111 -
b1110011000000000000000000000000000000000000000000000000000000000111110101110000 /
1+
b110100 *
b110100 ,
#16000
0+
#17000
b1000110 !
b1000110 4
b1000110 "
b1000110 3
b0 '
b0 .
b1110000000000000000000000000000000000000000000000000000000000000100011000000000 /
1+
b111101 *
b111101 ,
#18000
0+
#19000
b1000111 !
b1000111 4
1)
b0 (
b0 -
b0xxxxxxxxxxxxxxxxxxxxxxxxxxxxxxxxxxxxxxxxxxxxxxxxxxxxxxxxxxxxxxxxxxxxxxxx /
1+
b1000110 *
b1000110 ,
#20000
0+
#21000
1%
bx '
bx .
bx (
bx -
bx /
1+
b1000111 *
b1000111 ,
#22000
0+
#23000
1&
1+
b10000000000 *
b10000000000 ,
